{"cod_amm":"pvcsp","des_amm":"Parchi Val di Cornia S.P.A.","Comune":"Piombino","nome_resp":"Francesco","cogn_resp":"Ghizzani Marcia","Cap":"57025","Provincia":"LI","Regione":"Toscana","sito_istituzionale":"www.parchivaldicornia.it","Indirizzo":"Via Lerario N. 90","titolo_resp":"Presidente","tipologia_istat":"Societa' in Conto Economico Consolidato","tipologia_amm":"Societa' in Conto Economico Consolidato","acronimo":"","cf_validato":"S","Cf":"01091280493","mail1":"parchivaldicornia@pcert.postecert.it","tipo_mail1":"pec","mail2":"gasperinim@parchivaldicornia.it","tipo_mail2":"altro","mail3":"null","tipo_mail3":"null","mail4":"null","tipo_mail4":"null","mail5":"null","tipo_mail5":"null","url_facebook":"https://www.facebook.com/parchivaldicornia/","url_twitter":"https://twitter.com/parchivalcornia","url_googleplus":"https://plus.google.com/b/105843843900491008174/105843843900491008174","url_youtube":"https://www.youtube.com/channel/UCRJB_rmI-I5DtzJv0NdjQ2w?view_as=subscriber","liv_accessibili":"0"}
