{"cod_amm":"cfi","des_amm":"Consorzio Farmaceutico Intercomunale","Comune":"Salerno","nome_resp":"Francesco","cogn_resp":"Sorrentino","Cap":"84131","Provincia":"SA","Regione":"Campania","sito_istituzionale":"www.consorfarm.it","Indirizzo":"Via San Leonardo Trav. Migliaro","titolo_resp":"Direttore Generale","tipologia_istat":"Comuni e loro Consorzi e Associazioni","tipologia_amm":"Pubbliche Amministrazioni","acronimo":"","cf_validato":"S","Cf":"03406400659","mail1":"salerno@assofarm.postecert.it","tipo_mail1":"pec","mail2":"r.nesi@consofarm.it","tipo_mail2":"altro","mail3":"null","tipo_mail3":"null","mail4":"null","tipo_mail4":"null","mail5":"null","tipo_mail5":"null","url_facebook":"","url_twitter":"","url_googleplus":"","url_youtube":"","liv_accessibili":"0"}
