{"cod_amm":"cgppe","des_amm":"Collegio Geometri della Provincia di Pescara","Comune":"Pescara","nome_resp":"Tiziana","cogn_resp":"Finaguerra","Cap":"65122","Provincia":"PE","Regione":"Abruzzo","sito_istituzionale":"www.collegiogeometripescara.it","Indirizzo":"Piazza Della Rinascita, 69","titolo_resp":"Presidente","tipologia_istat":"Federazioni Nazionali, Ordini, Collegi e Consigli Professionali","tipologia_amm":"Pubbliche Amministrazioni","acronimo":"","cf_validato":"S","Cf":"80009170681","mail1":"collegio.pescara@geopec.it","tipo_mail1":"pec","mail2":"collegiopescara@virgilio.it","tipo_mail2":"altro","mail3":"null","tipo_mail3":"null","mail4":"null","tipo_mail4":"null","mail5":"null","tipo_mail5":"null","url_facebook":"","url_twitter":"","url_googleplus":"","url_youtube":"","liv_accessibili":"0"}
