{"cod_amm":"iedr","des_amm":"Ipab Emma e Decio Ripandelli","Comune":"Candela","nome_resp":"Nicola","cogn_resp":"Gatta","Cap":"71024","Provincia":"FG","Regione":"Puglia","sito_istituzionale":"www.enteripandelli.it","Indirizzo":"Via Orto Pennella 20","titolo_resp":"Sindaco Presidente","tipologia_istat":"Aziende Pubbliche di Servizi alla Persona","tipologia_amm":"Pubbliche Amministrazioni","acronimo":"","cf_validato":"S","Cf":"80001800715","mail1":"ipabripandelli@pec.it","tipo_mail1":"pec","mail2":"null","tipo_mail2":"null","mail3":"null","tipo_mail3":"null","mail4":"null","tipo_mail4":"null","mail5":"null","tipo_mail5":"null","url_facebook":"","url_twitter":"","url_googleplus":"","url_youtube":"","liv_accessibili":"0"}
