{"cod_amm":"istsc_psic82100c","des_amm":"ISTITUTO COMPRENSIVO - PESARO 'A.OLIVIERI'","Comune":"Pesaro","nome_resp":"ROBERTO","cogn_resp":"FRANCA","Cap":"61122","Provincia":"PU","Regione":"Marche","sito_istituzionale":"icolivieripesaro.gov.it/","Indirizzo":"Via Confalonieri 9","titolo_resp":"Dirigente Scolastico","tipologia_istat":"Istituti di Istruzione Statale di Ogni Ordine e Grado","tipologia_amm":"Pubbliche Amministrazioni","acronimo":"","cf_validato":"S","Cf":"80005610417","mail1":"psic82100c@pec.istruzione.it","tipo_mail1":"pec","mail2":"PSIC82100C@ISTRUZIONE.IT","tipo_mail2":"altro","mail3":"null","tipo_mail3":"null","mail4":"null","tipo_mail4":"null","mail5":"null","tipo_mail5":"null","url_facebook":"","url_twitter":"","url_googleplus":"","url_youtube":"","liv_accessibili":"0"}
