{"cod_amm":"cciaa_no","des_amm":"Camera di Commercio, Industria, Artigianato e Agricoltura di Novara","Comune":"Novara","nome_resp":"Cristina","cogn_resp":"D'Ercole","Cap":"28100","Provincia":"NO","Regione":"Piemonte","sito_istituzionale":"www.no.camcom.gov.it","Indirizzo":"Via degli Avogadro, 4","titolo_resp":"Segretario Generale","tipologia_istat":"Camere di Commercio, Industria, Artigianato e Agricoltura e loro Unioni Regionali","tipologia_amm":"Pubbliche Amministrazioni","acronimo":"","cf_validato":"S","Cf":"80008390033","mail1":"affari.generali@no.legalmail.camcom.it","tipo_mail1":"pec","mail2":"urp@no.camcom.it","tipo_mail2":"altro","mail3":"null","tipo_mail3":"null","mail4":"null","tipo_mail4":"null","mail5":"null","tipo_mail5":"null","url_facebook":"","url_twitter":"@camcom_novara","url_googleplus":"","url_youtube":"","liv_accessibili":"0"}
