{"cod_amm":"odipp_07","des_amm":"Ordine Degli Ingegneri della Provincia di Potenza","Comune":"Potenza","nome_resp":"Giuseppe","cogn_resp":"D'Onofrio","Cap":"85100","Provincia":"PZ","Regione":"Basilicata","sito_istituzionale":"www.ordingpz.it","Indirizzo":"Via D. Di Giura","titolo_resp":"Presidente","tipologia_istat":"Federazioni Nazionali, Ordini, Collegi e Consigli Professionali","tipologia_amm":"Pubbliche Amministrazioni","acronimo":"","cf_validato":"S","Cf":"80004080760","mail1":"ordine.potenza@ingpec.eu","tipo_mail1":"pec","mail2":"posta@ordingpz.it","tipo_mail2":"altro","mail3":"null","tipo_mail3":"null","mail4":"null","tipo_mail4":"null","mail5":"null","tipo_mail5":"null","url_facebook":"","url_twitter":"","url_googleplus":"","url_youtube":"","liv_accessibili":"0"}
