{"cod_amm":"cipas","des_amm":"Collegio degli Infermieri Professionali Assistenti Sanitari e Vigilatrici d'Infanzia (Ipasvi) della Provincia di Piacenza","Comune":"Piacenza","nome_resp":"Antonella","cogn_resp":"Gioia","Cap":"29122","Provincia":"PC","Regione":"Emilia Romagna","sito_istituzionale":"www.ipasvipc.it","Indirizzo":"Via Martiri Della Resistenza 10","titolo_resp":"Presidente Pro-tempore","tipologia_istat":"Federazioni Nazionali, Ordini, Collegi e Consigli Professionali","tipologia_amm":"Pubbliche Amministrazioni","acronimo":"IPASVI","cf_validato":"S","Cf":"80010910331","mail1":"piacenza@ipasvi.legalmail.it","tipo_mail1":"pec","mail2":"segreteria@ipasvipc.it","tipo_mail2":"altro","mail3":"null","tipo_mail3":"null","mail4":"null","tipo_mail4":"null","mail5":"null","tipo_mail5":"null","url_facebook":"","url_twitter":"","url_googleplus":"","url_youtube":"","liv_accessibili":"0"}
