{"cod_amm":"cdggl_an","des_amm":"Collegio dei Geometri e dei Geometri Laureati della Provincia di Ancona","Comune":"Ancona","nome_resp":"Diego","cogn_resp":"Sbaffi","Cap":"60121","Provincia":"AN","Regione":"Marche","sito_istituzionale":"www.geometrian.it","Indirizzo":"Corso Garibaldi N. 91/A","titolo_resp":"Presidente","tipologia_istat":"Federazioni Nazionali, Ordini, Collegi e Consigli Professionali","tipologia_amm":"Pubbliche Amministrazioni","acronimo":"COLLEGIO GEOMETRI ANCONA","cf_validato":"S","Cf":"80011050426","mail1":"collegio.ancona@geopec.it","tipo_mail1":"pec","mail2":"info@geometrian.it","tipo_mail2":"altro","mail3":"null","tipo_mail3":"null","mail4":"null","tipo_mail4":"null","mail5":"null","tipo_mail5":"null","url_facebook":"","url_twitter":"","url_googleplus":"","url_youtube":"","liv_accessibili":"0"}
