{"cod_amm":"istsc_BAIS042002","des_amm":"ISTITUTO SUPERIORE - AMERIGO VESPUCCI","Comune":"Molfetta","nome_resp":"FRANCESCO","cogn_resp":"ALLEGRETTA","Cap":"70056","Provincia":"BA","Regione":"Puglia","sito_istituzionale":"www.ipisiamvespucci.com","Indirizzo":"STRADA VICINALE TORRE ROTONDA","titolo_resp":"Dirigente Scolastico","tipologia_istat":"Istituti di Istruzione Statale di Ogni Ordine e Grado","tipologia_amm":"Pubbliche Amministrazioni","acronimo":"","cf_validato":"S","Cf":"80021490729","mail1":"BAIS042002@pec.istruzione.it","tipo_mail1":"pec","mail2":"BAIS042002@istruzione.it","tipo_mail2":"altro","mail3":"null","tipo_mail3":"null","mail4":"null","tipo_mail4":"null","mail5":"null","tipo_mail5":"null","url_facebook":"","url_twitter":"","url_googleplus":"","url_youtube":"","liv_accessibili":"0"}
