{"cod_amm":"fptmte","des_amm":"Fondazione Piccolo Teatro di Milano Teatro D'Europa","Comune":"Milano","nome_resp":"Carmen Lucia","cogn_resp":"Spiazzi","Cap":"20121","Provincia":"MI","Regione":"Lombardia","sito_istituzionale":"www.piccoloteatro.org","Indirizzo":"Via Rovello, 2","titolo_resp":"Procuratore Del Legale Rappresentante","tipologia_istat":"Teatri Stabili ad Iniziativa Pubblica","tipologia_amm":"Pubbliche Amministrazioni","acronimo":"","cf_validato":"S","Cf":"00802230151","mail1":"piccoloteatromilano@pec.it","tipo_mail1":"pec","mail2":"null","tipo_mail2":"null","mail3":"null","tipo_mail3":"null","mail4":"null","tipo_mail4":"null","mail5":"null","tipo_mail5":"null","url_facebook":"","url_twitter":"","url_googleplus":"","url_youtube":"","liv_accessibili":"0"}
