{"cod_amm":"istsc_pvra02000d","des_amm":"ISTITUTO PROFESSIONALE PER L'AGRICOLTURA E L'AMBIENTE - CIRO POLLINI - MORTARA","Comune":"Mortara","nome_resp":"ELDA","cogn_resp":"FROJO","Cap":"27036","Provincia":"PV","Regione":"Lombardia","sito_istituzionale":"ciropollini.gov.it","Indirizzo":"Via Ospedale n.4","titolo_resp":"Dirigente Scolastico","tipologia_istat":"Istituti di Istruzione Statale di Ogni Ordine e Grado","tipologia_amm":"Pubbliche Amministrazioni","acronimo":"","cf_validato":"S","Cf":"92001090189","mail1":"pvra02000d@pec.istruzione.it","tipo_mail1":"pec","mail2":"pvra02000d@ciropollini.eu","tipo_mail2":"altro","mail3":"null","tipo_mail3":"null","mail4":"null","tipo_mail4":"null","mail5":"null","tipo_mail5":"null","url_facebook":"","url_twitter":"","url_googleplus":"","url_youtube":"","liv_accessibili":"0"}
