{"cod_amm":"clddl","des_amm":"Consorzio per La Depurazione Dei Liquami Tra I Comuni di Giarre Riposto Mascali Fiumefreddo di Sicilia Sant'Alfio","Comune":"Mascali","nome_resp":"Giovanni","cogn_resp":"Spada","Cap":"95016","Provincia":"CT","Regione":"Sicilia","sito_istituzionale":"","Indirizzo":"Via San Giuseppe, 148","titolo_resp":"Presidente Consiglio Di Amministrazione","tipologia_istat":"Consorzi tra Amministrazioni Locali","tipologia_amm":"Pubbliche Amministrazioni","acronimo":"","cf_validato":"S","Cf":"92001220877","mail1":"codel@pcert.postecert.it","tipo_mail1":"pec","mail2":"null","tipo_mail2":"null","mail3":"null","tipo_mail3":"null","mail4":"null","tipo_mail4":"null","mail5":"null","tipo_mail5":"null","url_facebook":"","url_twitter":"","url_googleplus":"","url_youtube":"","liv_accessibili":"0"}
