{"cod_amm":"cea","des_amm":"C.E.A. Centro di Educazione Ambientale Delle Serre Salentine","Comune":"Poggiardo","nome_resp":"Antonio","cogn_resp":"Fitto","Cap":"73037","Provincia":"LE","Regione":"Puglia","sito_istituzionale":"www.ceaserresalentine.it","Indirizzo":"Via A. Moro, 1","titolo_resp":"Presidente Cda","tipologia_istat":"Comuni e loro Consorzi e Associazioni","tipologia_amm":"Pubbliche Amministrazioni","acronimo":"CEA","cf_validato":"S","Cf":"92016250752","mail1":"ceasalento@pec.it","tipo_mail1":"pec","mail2":"null","tipo_mail2":"null","mail3":"null","tipo_mail3":"null","mail4":"null","tipo_mail4":"null","mail5":"null","tipo_mail5":"null","url_facebook":"","url_twitter":"","url_googleplus":"","url_youtube":"","liv_accessibili":"0"}
