{"cod_amm":"istsc_vric860003","des_amm":"Istituto Comprensivo Tregnago Badia Calavena","Comune":"Tregnago","nome_resp":"BIANCHI","cogn_resp":"MAURIZIO","Cap":"37039","Provincia":"VR","Regione":"Veneto","sito_istituzionale":"www.ictregnago.gov.it","Indirizzo":"VIA ARCH. G.C. PELLEGRINI CIPOLLA  8","titolo_resp":"Dirigente Scolastico","tipologia_istat":"Istituti di Istruzione Statale di Ogni Ordine e Grado","tipologia_amm":"Pubbliche Amministrazioni","acronimo":"","cf_validato":"S","Cf":"92012450232","mail1":"vric860003@pec.istruzione.it","tipo_mail1":"pec","mail2":"vric860003@istruzione.it","tipo_mail2":"altro","mail3":"null","tipo_mail3":"null","mail4":"null","tipo_mail4":"null","mail5":"null","tipo_mail5":"null","url_facebook":"","url_twitter":"","url_googleplus":"","url_youtube":"","liv_accessibili":"0"}
