{"cod_amm":"aopso_bo","des_amm":"Azienda Ospedaliero-Universitaria di Bologna Policlinico Sant'Orsola-Malpighi","Comune":"Bologna","nome_resp":"ANTONELLA","cogn_resp":"MESSORI","Cap":"40138","Provincia":"BO","Regione":"Emilia Romagna","sito_istituzionale":"www.aosp.bo.it","Indirizzo":"Via Albertoni,15","titolo_resp":"Direttore Generale","tipologia_istat":"Aziende Ospedaliere, Aziende Ospedaliere Universitarie, Policlinici e Istituti di Ricovero e Cura a Carattere Scientifico Pubblici","tipologia_amm":"Pubbliche Amministrazioni","acronimo":"","cf_validato":"S","Cf":"92038610371","mail1":"PEIdirezione.generale@pec.aosp.bo.it","tipo_mail1":"pec","mail2":"null","tipo_mail2":"null","mail3":"null","tipo_mail3":"null","mail4":"null","tipo_mail4":"null","mail5":"null","tipo_mail5":"null","url_facebook":"","url_twitter":"","url_googleplus":"","url_youtube":"","liv_accessibili":"2"}
