{"cod_amm":"cplidacb","des_amm":"Centro Provinciale per L'Istruzione Degli Adulti Campobasso","Comune":"Campobasso","nome_resp":"AGATA","cogn_resp":"ANTONELLI","Cap":"86100","Provincia":"CB","Regione":"Molise","sito_istituzionale":"www.cpiacampobasso.gov.it","Indirizzo":"Via Delle Frasche, 44","titolo_resp":"Dirigente Scolastico","tipologia_istat":"Istituti di Istruzione Statale di Ogni Ordine e Grado","tipologia_amm":"Pubbliche Amministrazioni","acronimo":"istsccbmm205005","cf_validato":"S","Cf":"92071940701","mail1":"cbmm205005@pec.istruzione.it","tipo_mail1":"pec","mail2":"cbmm205005@istruzione.it","tipo_mail2":"altro","mail3":"null","tipo_mail3":"null","mail4":"null","tipo_mail4":"null","mail5":"null","tipo_mail5":"null","url_facebook":"","url_twitter":"","url_googleplus":"","url_youtube":"","liv_accessibili":"0"}
