{"cod_amm":"istsc_cais004004","des_amm":"ISTRUZIONE SECONDARIA SUPERIORE - I.I.S.S. GIUSEPPE DESSI","Comune":"Villaputzu","nome_resp":"PASQUALE","cogn_resp":"NUGNES","Cap":"09040","Provincia":"CA","Regione":"Sardegna","sito_istituzionale":"professionalevillaputzu.gov.it","Indirizzo":"Piazza Galileo Galilei N. 3","titolo_resp":"Dirigente Scolastico","tipologia_istat":"Istituti di Istruzione Statale di Ogni Ordine e Grado","tipologia_amm":"Pubbliche Amministrazioni","acronimo":"","cf_validato":"S","Cf":"92104860926","mail1":"CAIS004004@pec.ISTRUZIONE.IT","tipo_mail1":"pec","mail2":"cais004004@istruzione.it","tipo_mail2":"altro","mail3":"null","tipo_mail3":"null","mail4":"null","tipo_mail4":"null","mail5":"null","tipo_mail5":"null","url_facebook":"","url_twitter":"","url_googleplus":"","url_youtube":"","liv_accessibili":"0"}
