{"cod_amm":"udal_98","des_amm":"Ufficio D'Ambito di Lodi","Comune":"Lodi","nome_resp":"Diomira Caterina Ida","cogn_resp":"Cretti","Cap":"26900","Provincia":"LO","Regione":"Lombardia","sito_istituzionale":"www.provincia.lodi.it","Indirizzo":"Via Fanfulla, 14","titolo_resp":"Direttore","tipologia_istat":"Enti di Regolazione dei Servizi Idrici e o dei Rifiuti","tipologia_amm":"Pubbliche Amministrazioni","acronimo":"","cf_validato":"S","Cf":"92557920151","mail1":"ufficioato.lodi@pec.regione.lombardia.it","tipo_mail1":"pec","mail2":"segreteria.ato@provincia.lodi.it","tipo_mail2":"altro","mail3":"null","tipo_mail3":"null","mail4":"null","tipo_mail4":"null","mail5":"null","tipo_mail5":"null","url_facebook":"","url_twitter":"","url_googleplus":"","url_youtube":"","liv_accessibili":"0"}
