{"cod_amm":"c_g597","des_amm":"Comune di Piedimonte Etneo","Comune":"Piedimonte Etneo","nome_resp":"Ignazio","cogn_resp":"Puglisi","Cap":"95017","Provincia":"CT","Regione":"Sicilia","sito_istituzionale":"www.comune.piedimonte-etneo.ct.it","Indirizzo":"Via Vittorio Emanuele II, 34","titolo_resp":"Sindaco","tipologia_istat":"Comuni e loro Consorzi e Associazioni","tipologia_amm":"Pubbliche Amministrazioni","acronimo":"","cf_validato":"S","Cf":"00671800878","mail1":"comune.piedimonte-etneo@pec.it","tipo_mail1":"pec","mail2":"pubblicazioni@comune.piedimonte-etneo.ct.it","tipo_mail2":"altro","mail3":"null","tipo_mail3":"null","mail4":"null","tipo_mail4":"null","mail5":"null","tipo_mail5":"null","url_facebook":"","url_twitter":"","url_googleplus":"","url_youtube":"","liv_accessibili":"1"}
