{"cod_amm":"c_h944","des_amm":"Comune di Sanguinetto","Comune":"Sanguinetto","nome_resp":"Alessandro","cogn_resp":"Braga","Cap":"37058","Provincia":"VR","Regione":"Veneto","sito_istituzionale":"www.sanguinetto.gov.it","Indirizzo":"Via Interno Castello 2","titolo_resp":"Sindaco","tipologia_istat":"Comuni e loro Consorzi e Associazioni","tipologia_amm":"Pubbliche Amministrazioni","acronimo":"","cf_validato":"S","Cf":"00661100230","mail1":"comune.sanguinetto.vr@pecveneto.it","tipo_mail1":"pec","mail2":"protocollo@comune.sanguinetto.vr.it","tipo_mail2":"altro","mail3":"null","tipo_mail3":"null","mail4":"null","tipo_mail4":"null","mail5":"null","tipo_mail5":"null","url_facebook":"","url_twitter":"","url_googleplus":"","url_youtube":"","liv_accessibili":"0"}
