{"cod_amm":"oddcd_2","des_amm":"Ordine Dei Dottori Commercialisti e Degli Esperti Contabili di Castrovillari","Comune":"Castrovillari","nome_resp":"Mario","cogn_resp":"Stratico'","Cap":"87012","Provincia":"CS","Regione":"Calabria","sito_istituzionale":"www.odceccastrovillari.it","Indirizzo":"Viale del Lavoro n. 128","titolo_resp":"Presidente","tipologia_istat":"Federazioni Nazionali, Ordini, Collegi e Consigli Professionali","tipologia_amm":"Pubbliche Amministrazioni","acronimo":"","cf_validato":"S","Cf":"94015500781","mail1":"segreteria@odceccv.legalmail.it","tipo_mail1":"pec","mail2":"odccv@tiscali.it","tipo_mail2":"altro","mail3":"null","tipo_mail3":"null","mail4":"null","tipo_mail4":"null","mail5":"null","tipo_mail5":"null","url_facebook":"","url_twitter":"","url_googleplus":"","url_youtube":"","liv_accessibili":"0"}
