{"cod_amm":"c_b826","des_amm":"Comune di Carpineto Sinello","Comune":"Carpineto Sinello","nome_resp":"Antonio","cogn_resp":"Colonna","Cap":"66030","Provincia":"CH","Regione":"Abruzzo","sito_istituzionale":"www.comune.carpinetosinello.ch.it","Indirizzo":"Via Rotabile Provinciale, 11","titolo_resp":"Sindaco","tipologia_istat":"Comuni e loro Consorzi e Associazioni","tipologia_amm":"Pubbliche Amministrazioni","acronimo":"","cf_validato":"S","Cf":"00254060692","mail1":"comune.carpinetosinello@pec.it","tipo_mail1":"pec","mail2":"ragioneria.carpineto@gmail.com","tipo_mail2":"altro","mail3":"null","tipo_mail3":"null","mail4":"null","tipo_mail4":"null","mail5":"null","tipo_mail5":"null","url_facebook":"","url_twitter":"","url_googleplus":"","url_youtube":"","liv_accessibili":"3"}
