{"cod_amm":"iscmm","des_amm":"Istituzione Sociale Cesare e Mina Micheli","Comune":"Spoleto","nome_resp":"Valia","cogn_resp":"Fedeli Alianti","Cap":"06049","Provincia":"PG","Regione":"Umbria","sito_istituzionale":"","Indirizzo":"Via San Carlo,13","titolo_resp":"Legale Rappresentante","tipologia_istat":"Aziende Pubbliche di Servizi alla Persona","tipologia_amm":"Pubbliche Amministrazioni","acronimo":"","cf_validato":"S","Cf":"02992240545","mail1":"iscmm@certificazioneposta.it","tipo_mail1":"pec","mail2":"null","tipo_mail2":"null","mail3":"null","tipo_mail3":"null","mail4":"null","tipo_mail4":"null","mail5":"null","tipo_mail5":"null","url_facebook":"","url_twitter":"","url_googleplus":"","url_youtube":"","liv_accessibili":"0"}
