{"cod_amm":"adpspa","des_amm":"Acquedotto della Piana S.P.A.","Comune":"Villanova d'Asti","nome_resp":"Corrado","cogn_resp":"Meliga","Cap":"14019","Provincia":"AT","Regione":"Piemonte","sito_istituzionale":"www.acquedottopiana.it","Indirizzo":"Via Carlo V, 53","titolo_resp":"Presidenete e Amministratore Delegato","tipologia_istat":"Gestori di Pubblici Servizi","tipologia_amm":"Gestori di Pubblici Servizi","acronimo":"","cf_validato":"S","Cf":"00099020059","mail1":"acquedottopiana@legalmail.it","tipo_mail1":"pec","mail2":"null","tipo_mail2":"null","mail3":"null","tipo_mail3":"null","mail4":"null","tipo_mail4":"null","mail5":"null","tipo_mail5":"null","url_facebook":"","url_twitter":"","url_googleplus":"","url_youtube":"","liv_accessibili":"0"}
