{"cod_amm":"c_i639","des_amm":"Comune di Serre","Comune":"Serre","nome_resp":"Franco","cogn_resp":"Mennella","Cap":"84028","Provincia":"SA","Regione":"Campania","sito_istituzionale":"www.comune.serre.sa.it","Indirizzo":"Via Vittorio Emanuele","titolo_resp":"Sindaco","tipologia_istat":"Comuni e loro Consorzi e Associazioni","tipologia_amm":"Pubbliche Amministrazioni","acronimo":"","cf_validato":"S","Cf":"82001850658","mail1":"ufficio.aagg.serre@asmepec.it","tipo_mail1":"pec","mail2":"ufficio.anagrafe.serre@asmepec.it","tipo_mail2":"pec","mail3":"ufficio.tributi.serre@asmepec.it","tipo_mail3":"pec","mail4":"ufficio.tecnico.serre@asmepec.it","tipo_mail4":"pec","mail5":"fattura.serre@asmepec.it","tipo_mail5":"pec","url_facebook":"https://www.facebook.com/serre","url_twitter":"https://www.twitter.com/serre","url_googleplus":"https://plus.google.com/serre","url_youtube":"http://www.youtube.com/serre","liv_accessibili":"2"}
