{"description":"I Servizi Demografici emettono le Carte di Identità e stilano atti vari che necessitano di Bollo.   \nTramite IO potrai:\n\n* pagare la Carta d’Identità Elettronica o Cartacea;\n* pagare il Bollo Virtuale per gli atti pubblici\n* ricevere una conferma del pagamento avvenuto.\n","web_url":"https://comune.grottaglie.ta.it/privacy-policy/","phone":"099 5620217","email":"demografici@comune.grottaglie.ta.it","pec":"anagrafe.comunegrottaglie@pec.rupar.puglia.it","address":"Via Martiri d’Ungheria snc – 74023 Grottaglie (TA)","scope":"LOCAL"}