{"cod_amm":"istsc_rmrh02000c","des_amm":"ISTITUTO PROFESSIONALE PER I SERVIZI ALBERGHIERI E RISTORAZIONE - PELLEGRINO ARTUSI","Comune":"Roma","nome_resp":"MARIA PERLA","cogn_resp":"PUGLIESE","Cap":"00178","Provincia":"RM","Regione":"Lazio","sito_istituzionale":"","Indirizzo":"Via Pizzo Di Calabria,5","titolo_resp":"Dirigente Scolastico","tipologia_istat":"Istituti di Istruzione Statale di Ogni Ordine e Grado","tipologia_amm":"Pubbliche Amministrazioni","acronimo":"null","cf_validato":"S","Cf":"97110170582","mail1":"rmrh02000c@pec.istruzione.it","tipo_mail1":"pec","mail2":"null","tipo_mail2":"null","mail3":"null","tipo_mail3":"null","mail4":"null","tipo_mail4":"null","mail5":"null","tipo_mail5":"null","url_facebook":"","url_twitter":"","url_googleplus":"","url_youtube":"","liv_accessibili":"0"}
