{"cod_amm":"cinlf","des_amm":"CINFAI - Consorzio Nazionale Interuniversitario Per la Fisica delle Atmosfere e delle Idrosfere","Comune":"Tolentino","nome_resp":"Antonio","cogn_resp":"Speranza","Cap":"62029","Provincia":"MC","Regione":"Marche","sito_istituzionale":"","Indirizzo":"Piazza Niccolo' Mauruzi, 17","titolo_resp":"Presidente","tipologia_istat":"Consorzi Interuniversitari di Ricerca","tipologia_amm":"Pubbliche Amministrazioni","acronimo":"CINFAI","cf_validato":"S","Cf":"97578350015","mail1":"direzione.cinfai@registerpec.it","tipo_mail1":"pec","mail2":"null","tipo_mail2":"null","mail3":"null","tipo_mail3":"null","mail4":"null","tipo_mail4":"null","mail5":"null","tipo_mail5":"null","url_facebook":"","url_twitter":"","url_googleplus":"","url_youtube":"","liv_accessibili":"0"}
