{"cod_amm":"c_d266","des_amm":"Comune di Delebio","Comune":"Delebio","nome_resp":"Marco","cogn_resp":"Ioli","Cap":"23014","Provincia":"SO","Regione":"Lombardia","sito_istituzionale":"www.comune.delebio.so.it","Indirizzo":"Piazza S.Domenica,3","titolo_resp":"Sindaco","tipologia_istat":"Comuni e loro Consorzi e Associazioni","tipologia_amm":"Pubbliche Amministrazioni","acronimo":"","cf_validato":"S","Cf":"00097780142","mail1":"protocollo.delebio@cert.provincia.so.it","tipo_mail1":"pec","mail2":"amministrazione@comune.delebio.so.it","tipo_mail2":"altro","mail3":"null","tipo_mail3":"null","mail4":"null","tipo_mail4":"null","mail5":"null","tipo_mail5":"null","url_facebook":"","url_twitter":"","url_googleplus":"","url_youtube":"","liv_accessibili":"0"}
