{"cod_amm":"istsc_agis021005","des_amm":"ISTITUTO SUPERIORE - I.I.S. FRANCESCO CRISPI","Comune":"Ribera","nome_resp":"ANTONINA","cogn_resp":"TRIOLO","Cap":"92016","Provincia":"AG","Regione":"Sicilia","sito_istituzionale":"www.istitutosuperiorecrispiribera.gov.it","Indirizzo":"Via PRESTI, 2","titolo_resp":"Dirigente Scolastico","tipologia_istat":"Istituti di Istruzione Statale di Ogni Ordine e Grado","tipologia_amm":"Pubbliche Amministrazioni","acronimo":"","cf_validato":"S","Cf":"83002610844","mail1":"agis021005@pec.istruzione.it","tipo_mail1":"pec","mail2":"agis021005@istruzione.it","tipo_mail2":"altro","mail3":"null","tipo_mail3":"null","mail4":"null","tipo_mail4":"null","mail5":"null","tipo_mail5":"null","url_facebook":"","url_twitter":"","url_googleplus":"","url_youtube":"","liv_accessibili":"0"}
