{"cod_amm":"asbucsmv","des_amm":"Amministrazione Separata Beni Uso Civico S. Maddalena Valbassa","Comune":"Valle Di Casies","nome_resp":"Gabriel","cogn_resp":"Kahn","Cap":"39030","Provincia":"BZ","Regione":"Trentino Alto Adige","sito_istituzionale":"","Indirizzo":"Unterstein, 1","titolo_resp":"Presidente","tipologia_istat":"Altri Enti Locali","tipologia_amm":"Pubbliche Amministrazioni","acronimo":"","cf_validato":"S","Cf":"81006500219","mail1":"magdalena.niedertal@pec.rolmail.net","tipo_mail1":"pec","mail2":"magdalena.niedertal@rolmail.net","tipo_mail2":"altro","mail3":"null","tipo_mail3":"null","mail4":"null","tipo_mail4":"null","mail5":"null","tipo_mail5":"null","url_facebook":"","url_twitter":"","url_googleplus":"","url_youtube":"","liv_accessibili":"0"}
