{"cod_amm":"istsc_tvic81500d","des_amm":"ISTITUTO COMPRENSIVO - IC CASTELFRANCO V.TO 1","Comune":"Castelfranco Veneto","nome_resp":"MICHELA","cogn_resp":"BOLZON","Cap":"31033","Provincia":"TV","Regione":"Veneto","sito_istituzionale":"www.iccastelfranco1.it","Indirizzo":"Via A. Volta 3","titolo_resp":"Dirigente Scolastico","tipologia_istat":"Istituti di Istruzione Statale di Ogni Ordine e Grado","tipologia_amm":"Pubbliche Amministrazioni","acronimo":"","cf_validato":"S","Cf":"81002050268","mail1":"tvic81500d@pec.istruzione.it","tipo_mail1":"pec","mail2":"tvic81500d@istruzione.it","tipo_mail2":"altro","mail3":"null","tipo_mail3":"null","mail4":"null","tipo_mail4":"null","mail5":"null","tipo_mail5":"null","url_facebook":"","url_twitter":"","url_googleplus":"","url_youtube":"","liv_accessibili":"0"}
