{"cod_amm":"c_e914","des_amm":"Comune di Marano Marchesato","Comune":"Marano Marchesato","nome_resp":"Eduardo","cogn_resp":"Vivacqua","Cap":"87040","Provincia":"CS","Regione":"Calabria","sito_istituzionale":"www.comune.maranomarchesato.cs.it/","Indirizzo":"Via Kennedy","titolo_resp":"Sindaco","tipologia_istat":"Comuni e loro Consorzi e Associazioni","tipologia_amm":"Pubbliche Amministrazioni","acronimo":"","cf_validato":"S","Cf":"00390390789","mail1":"ragioneria.maranom@pcert.postecert.it","tipo_mail1":"pec","mail2":"comunemaranomarchesato@virgilio.it","tipo_mail2":"altro","mail3":"sindaco@comune.maranomarchesato.cs.it","tipo_mail3":"altro","mail4":"lavoripubblici.maranom@pcert.postecert.it","tipo_mail4":"pec","mail5":"urbanistica.maranom@pcert.postecert.it","tipo_mail5":"pec","url_facebook":"","url_twitter":"","url_googleplus":"","url_youtube":"","liv_accessibili":"0"}
