{"cod_amm":"escarl","des_amm":"Euroleader Soc.Cons.A R.L.","Comune":"Tolmezzo","nome_resp":"Claudio","cogn_resp":"Cescutti","Cap":"33028","Provincia":"UD","Regione":"Friuli Venezia Giulia","sito_istituzionale":"www.euroleader.it","Indirizzo":"Via Carnia Libera 1944, 15","titolo_resp":"Legale Rappresentante","tipologia_istat":"Gestori di Pubblici Servizi","tipologia_amm":"Gestori di Pubblici Servizi","acronimo":"EUROLEADER","cf_validato":"S","Cf":"02225450309","mail1":"euroleader@legalmail.it","tipo_mail1":"pec","mail2":"info@euroleadre.it","tipo_mail2":"altro","mail3":"null","tipo_mail3":"null","mail4":"null","tipo_mail4":"null","mail5":"null","tipo_mail5":"null","url_facebook":"http//euroleader","url_twitter":"","url_googleplus":"","url_youtube":"","liv_accessibili":"0"}
