{"cod_amm":"asstu","des_amm":"Area Stazione Societa' di Trasformazione Urbana S.P.A.","Comune":"Parma","nome_resp":"Isabella","cogn_resp":"Tagliavini","Cap":"43121","Provincia":"PR","Regione":"Emilia Romagna","sito_istituzionale":"www.stuareastazione.it","Indirizzo":"Viale Giovanni Falcone 30 A","titolo_resp":"Amministratore Unico","tipologia_istat":"Societa' in Conto Economico Consolidato","tipologia_amm":"Societa' in Conto Economico Consolidato","acronimo":"","cf_validato":"S","Cf":"02280810348","mail1":"amministrazione@pec.sttholding.it","tipo_mail1":"pec","mail2":"i.tagliavini@areastazione.sttholding.it","tipo_mail2":"altro","mail3":"g.capotorto@sttholding.it","tipo_mail3":"altro","mail4":"null","tipo_mail4":"null","mail5":"null","tipo_mail5":"null","url_facebook":"","url_twitter":"","url_googleplus":"","url_youtube":"","liv_accessibili":"0"}
