{"cod_amm":"ulvpo","des_amm":"Unione Lombarda Valle del Po","Comune":"Barbianello","nome_resp":"Gabriele","cogn_resp":"Maggiori","Cap":"27041","Provincia":"PV","Regione":"Lombardia","sito_istituzionale":"www.unionevalledelpo.it","Indirizzo":"Via Roma, 5","titolo_resp":"Segretario Comunale","tipologia_istat":"Unioni di Comuni e loro Consorzi e Associazioni","tipologia_amm":"Pubbliche Amministrazioni","acronimo":"","cf_validato":"S","Cf":"93007900181","mail1":"unionevalledelpo@pcert.it","tipo_mail1":"pec","mail2":"null","tipo_mail2":"null","mail3":"null","tipo_mail3":"null","mail4":"null","tipo_mail4":"null","mail5":"null","tipo_mail5":"null","url_facebook":"","url_twitter":"","url_googleplus":"","url_youtube":"","liv_accessibili":"0"}
