{"cod_amm":"ipabcmg","des_amm":"IPAB Casa di Riposo Maria Gasparini di Villa Bartolomea","Comune":"Villa Bartolomea","nome_resp":"Maurizio","cogn_resp":"Pastorello","Cap":"37049","Provincia":"VR","Regione":"Veneto","sito_istituzionale":"www.ipabcasadiriposomariagasparini.it/","Indirizzo":"Corso Fraccaroli, 81","titolo_resp":"Segretario-Direttore","tipologia_istat":"Aziende Pubbliche di Servizi alla Persona","tipologia_amm":"Pubbliche Amministrazioni","acronimo":"","cf_validato":"S","Cf":"04399910233","mail1":"ipabcasadiriposomariagasparini@pec.it","tipo_mail1":"pec","mail2":"info@ipabcasadiriposomariagasparini.it","tipo_mail2":"altro","mail3":"null","tipo_mail3":"null","mail4":"null","tipo_mail4":"null","mail5":"null","tipo_mail5":"null","url_facebook":"","url_twitter":"","url_googleplus":"","url_youtube":"","liv_accessibili":"0"}
