{"cod_amm":"C_I216","des_amm":"Comune di Sant'Alfio","Comune":"Sant'Alfio","nome_resp":"Giuseppe Maria","cogn_resp":"Nicotra","Cap":"95010","Provincia":"CT","Regione":"Sicilia","sito_istituzionale":"www.comunesantalfio.gov.it","Indirizzo":"Via Vitt. Emanuele, 4","titolo_resp":"Sindaco","tipologia_istat":"Comuni e loro Consorzi e Associazioni","tipologia_amm":"Pubbliche Amministrazioni","acronimo":"","cf_validato":"S","Cf":"00230090870","mail1":"protocollosantalfio@pec.it","tipo_mail1":"pec","mail2":"protocollo@comunesantalfio.gov.it","tipo_mail2":"altro","mail3":"sindaco@comunesantalfio.gov.it","tipo_mail3":"altro","mail4":"null","tipo_mail4":"null","mail5":"null","tipo_mail5":"null","url_facebook":"","url_twitter":"","url_googleplus":"","url_youtube":"","liv_accessibili":"0"}
