{"cod_amm":"csc","des_amm":"Centro Servizi Condivisi","Comune":"Rovereto","nome_resp":"Monica","cogn_resp":"Baggia","Cap":"38068","Provincia":"TN","Regione":"Trentino Alto Adige","sito_istituzionale":"","Indirizzo":"Via Fortunato Zeni, 8","titolo_resp":"Coordinatrice Organo Amministrativo","tipologia_istat":"Gestori di Pubblici Servizi","tipologia_amm":"Gestori di Pubblici Servizi","acronimo":"","cf_validato":"S","Cf":"02307490223","mail1":"ccsc@pec.ccsc.it","tipo_mail1":"pec","mail2":"info@ccsc.it","tipo_mail2":"altro","mail3":"null","tipo_mail3":"null","mail4":"null","tipo_mail4":"null","mail5":"null","tipo_mail5":"null","url_facebook":"","url_twitter":"","url_googleplus":"","url_youtube":"","liv_accessibili":"0"}
