{"cod_amm":"uctvp_00","des_amm":"Unione Collinare Terre di Vigneti e Pietra da Cantoni","Comune":"Rosignano Monferrato","nome_resp":"Rossella","cogn_resp":"Piattelli","Cap":"15030","Provincia":"AL","Regione":"Piemonte","sito_istituzionale":"www.unionevignetiecantoni.al.it","Indirizzo":"Via Roma 19","titolo_resp":"Segretario","tipologia_istat":"Unioni di Comuni e loro Consorzi e Associazioni","tipologia_amm":"Pubbliche Amministrazioni","acronimo":"","cf_validato":"S","Cf":"02395430065","mail1":"unioneterredivigneti@pec.e-volution.it","tipo_mail1":"pec","mail2":"info@unionevignetiecantoni.al.it","tipo_mail2":"altro","mail3":"null","tipo_mail3":"null","mail4":"null","tipo_mail4":"null","mail5":"null","tipo_mail5":"null","url_facebook":"","url_twitter":"","url_googleplus":"","url_youtube":"","liv_accessibili":"2"}
