{"cod_amm":"C_f661","des_amm":"Comune di Monteverdi Marittimo","Comune":"Monteverdi Marittimo","nome_resp":"Carlo","cogn_resp":"Giannoni","Cap":"56040","Provincia":"PI","Regione":"Toscana","sito_istituzionale":"www.comune.monteverdi.pi.it","Indirizzo":"Via IV Novembre, 1","titolo_resp":"Sindaco","tipologia_istat":"Comuni e loro Consorzi e Associazioni","tipologia_amm":"Pubbliche Amministrazioni","acronimo":"","cf_validato":"S","Cf":"00187490503","mail1":"comune.monteverdi.m@postacert.toscana.it","tipo_mail1":"pec","mail2":"comune.monteverdi@comune.monteverdi.pi.ut","tipo_mail2":"altro","mail3":"null","tipo_mail3":"null","mail4":"null","tipo_mail4":"null","mail5":"null","tipo_mail5":"null","url_facebook":"","url_twitter":"","url_googleplus":"","url_youtube":"","liv_accessibili":"3"}
