{"cod_amm":"istsc_CEIC812009","des_amm":"ISTITUTO COMPRENSIVO - I.A.C.'VENTRIGLIA'- PIEDIMONTE","Comune":"Piedimonte Matese","nome_resp":"DIAMANTE","cogn_resp":"MAROTTA","Cap":"81016","Provincia":"CE","Regione":"Campania","sito_istituzionale":"www.icventriglia.gov.it","Indirizzo":"Via Angelo Scorciarini Coppola, 198","titolo_resp":"Dirigente Scolastico","tipologia_istat":"Istituti di Istruzione Statale di Ogni Ordine e Grado","tipologia_amm":"Pubbliche Amministrazioni","acronimo":"","cf_validato":"S","Cf":"91005050611","mail1":"CEIC812009@pec.istruzione.it","tipo_mail1":"pec","mail2":"CEIC812009@istruzione.it","tipo_mail2":"altro","mail3":"null","tipo_mail3":"null","mail4":"null","tipo_mail4":"null","mail5":"null","tipo_mail5":"null","url_facebook":"","url_twitter":"","url_googleplus":"","url_youtube":"","liv_accessibili":"0"}
