{"cod_amm":"cpdadagr","des_amm":"Collegio Provinciale Degli Agrotecnici e Degli Agrotecnici Laureati di Rovigo","Comune":"Occhiobello","nome_resp":"Angelo","cogn_resp":"Zanellato","Cap":"45030","Provincia":"RO","Regione":"Veneto","sito_istituzionale":"www.agrotecnicirovigo.it","Indirizzo":"Via Eridania, 130","titolo_resp":"Presidente","tipologia_istat":"Federazioni Nazionali, Ordini, Collegi e Consigli Professionali","tipologia_amm":"Pubbliche Amministrazioni","acronimo":"","cf_validato":"S","Cf":"91001770295","mail1":"rovigo@pecagrotecnici.it","tipo_mail1":"pec","mail2":"null","tipo_mail2":"null","mail3":"null","tipo_mail3":"null","mail4":"null","tipo_mail4":"null","mail5":"null","tipo_mail5":"null","url_facebook":"","url_twitter":"","url_googleplus":"","url_youtube":"","liv_accessibili":"0"}
