{"cod_amm":"icgpc","des_amm":"Istituto Comprensivo G.Pascoli di Colliano","Comune":"Colliano","nome_resp":"Ornella","cogn_resp":"Pellegrino","Cap":"84020","Provincia":"SA","Regione":"Campania","sito_istituzionale":"www.iccolliano.gov.it","Indirizzo":"Via Luigi Cardone","titolo_resp":"Dirigente Scolastico","tipologia_istat":"Istituti di Istruzione Statale di Ogni Ordine e Grado","tipologia_amm":"Pubbliche Amministrazioni","acronimo":"ISTSCSAIC8A200N","cf_validato":"S","Cf":"91053500657","mail1":"SAIC8A200N@PEC.ISTRUZIONE.IT","tipo_mail1":"pec","mail2":"SAIC8A200N@ISTRUZIONE.IT","tipo_mail2":"altro","mail3":"null","tipo_mail3":"null","mail4":"null","tipo_mail4":"null","mail5":"null","tipo_mail5":"null","url_facebook":"","url_twitter":"","url_googleplus":"","url_youtube":"","liv_accessibili":"0"}
