{"cod_amm":"istsc_vaic879002","des_amm":"ISTITUTO COMPRENSIVO - I.C. SESTO CALENDE 'UNGARETTI'","Comune":"Sesto Calende","nome_resp":"ELISABETTA","cogn_resp":"ROSSI","Cap":"21018","Provincia":"VA","Regione":"Lombardia","sito_istituzionale":"www.icsestocalende.gov.it/","Indirizzo":"Via M. Bogni, 2","titolo_resp":"Dirigente Scolastico","tipologia_istat":"Istituti di Istruzione Statale di Ogni Ordine e Grado","tipologia_amm":"Pubbliche Amministrazioni","acronimo":"","cf_validato":"S","Cf":"91061130125","mail1":"vaic879002@pec.istruzione.it","tipo_mail1":"pec","mail2":"vaic879002@istruzione.it","tipo_mail2":"altro","mail3":"null","tipo_mail3":"null","mail4":"null","tipo_mail4":"null","mail5":"null","tipo_mail5":"null","url_facebook":"","url_twitter":"","url_googleplus":"","url_youtube":"","liv_accessibili":"0"}
