{"cod_amm":"istsc_reic85300e","des_amm":"ISTITUTO COMPRENSIVO - I.C. 'CORREGGIO 1'","Comune":"Correggio","nome_resp":"LUCIANO","cogn_resp":"CASELLI","Cap":"42015","Provincia":"RE","Regione":"Emilia Romagna","sito_istituzionale":"www.iccorreggio1.gov.it","Indirizzo":"Via Conte Ippolito, 18","titolo_resp":"Dirigente Scolastico","tipologia_istat":"Istituti di Istruzione Statale di Ogni Ordine e Grado","tipologia_amm":"Pubbliche Amministrazioni","acronimo":"","cf_validato":"S","Cf":"91160750351","mail1":"reic85300e@pec.istruzione.it","tipo_mail1":"pec","mail2":"info@iccorreggio1.gov.it","tipo_mail2":"altro","mail3":"reic85300e@istruzione.it","tipo_mail3":"altro","mail4":"null","tipo_mail4":"null","mail5":"null","tipo_mail5":"null","url_facebook":"","url_twitter":"","url_googleplus":"","url_youtube":"","liv_accessibili":"0"}
