{"cod_amm":"c_e263","des_amm":"Comune di Guidonia Montecelio","Comune":"Guidonia Montecelio","nome_resp":"Michel","cogn_resp":"Barbet","Cap":"00012","Provincia":"RM","Regione":"Lazio","sito_istituzionale":"www.guidoniamontecelio.gov.it","Indirizzo":"p. G. Matteotti, 20","titolo_resp":"Sindaco","tipologia_istat":"Comuni e loro Consorzi e Associazioni","tipologia_amm":"Pubbliche Amministrazioni","acronimo":"","cf_validato":"S","Cf":"02777620580","mail1":"protocollo@pec.guidonia.org","tipo_mail1":"pec","mail2":"sindaco@guidonia.org","tipo_mail2":"altro","mail3":"null","tipo_mail3":"null","mail4":"null","tipo_mail4":"null","mail5":"null","tipo_mail5":"null","url_facebook":"","url_twitter":"","url_googleplus":"","url_youtube":"","liv_accessibili":"0"}
