{"cod_amm":"istsc_bgis033008","des_amm":"ISTRUZIONE SECONDARIA SUPERIORE - 'ZENALE E BUTINONE'","Comune":"Treviglio","nome_resp":"PAOLA","cogn_resp":"PELLEGRINI","Cap":"24047","Provincia":"BG","Regione":"Lombardia","sito_istituzionale":"www.zenale.it","Indirizzo":"Via Galvani, 7","titolo_resp":"Dirigente Scolastico","tipologia_istat":"Istituti di Istruzione Statale di Ogni Ordine e Grado","tipologia_amm":"Pubbliche Amministrazioni","acronimo":"","cf_validato":"S","Cf":"84003610163","mail1":"bgis033008@pec.istruzione.it","tipo_mail1":"pec","mail2":"bgis033008@istruzione.it","tipo_mail2":"altro","mail3":"dsga@zenale.it","tipo_mail3":"altro","mail4":"null","tipo_mail4":"null","mail5":"null","tipo_mail5":"null","url_facebook":"","url_twitter":"","url_googleplus":"","url_youtube":"","liv_accessibili":"2"}
