{"cod_amm":"atocn","des_amm":"Ente di Governo D'Ambito Territoriale Ottimale N. 4 Cuneese","Comune":"Cuneo","nome_resp":"Giuseppe","cogn_resp":"Giuliano","Cap":"12100","Provincia":"CN","Regione":"Piemonte","sito_istituzionale":"www.ato4cuneese.it","Indirizzo":"Corso Nizza, 21","titolo_resp":"DIRETTORE","tipologia_istat":"Enti di Regolazione dei Servizi Idrici e o dei Rifiuti","tipologia_amm":"Pubbliche Amministrazioni","acronimo":"","cf_validato":"S","Cf":"96068020047","mail1":"ato4cuneese@pec.ato4cuneese.it","tipo_mail1":"pec","mail2":"null","tipo_mail2":"null","mail3":"null","tipo_mail3":"null","mail4":"null","tipo_mail4":"null","mail5":"null","tipo_mail5":"null","url_facebook":"","url_twitter":"","url_googleplus":"","url_youtube":"","liv_accessibili":"0"}
