{"cod_amm":"apt","des_amm":"AUTORITA' DI SISTEMA PORTUALE DEL MAR IONIO","Comune":"Taranto","nome_resp":"Fulvio Lino","cogn_resp":"Di Blasio","Cap":"74123","Provincia":"TA","Regione":"Puglia","sito_istituzionale":"www.port.taranto.it","Indirizzo":"Porto Mercantile","titolo_resp":"Segretario Generale","tipologia_istat":"Autorita' Portuali","tipologia_amm":"Pubbliche Amministrazioni","acronimo":"","cf_validato":"S","Cf":"90048270731","mail1":"protocollo.autportta@postecert.it","tipo_mail1":"pec","mail2":"null","tipo_mail2":"null","mail3":"null","tipo_mail3":"null","mail4":"null","tipo_mail4":"null","mail5":"null","tipo_mail5":"null","url_facebook":"","url_twitter":"","url_googleplus":"","url_youtube":"","liv_accessibili":"0"}
