{"cod_amm":"c_f749","des_amm":"Comune di Morrovalle","Comune":"Morrovalle","nome_resp":"Stefano","cogn_resp":"Montemarani","Cap":"62010","Provincia":"MC","Regione":"Marche","sito_istituzionale":"www.comune.morrovalle.mc.it","Indirizzo":"Piazza Vittorio Emanuele II 1","titolo_resp":"Sindaco","tipologia_istat":"Comuni e loro Consorzi e Associazioni","tipologia_amm":"Pubbliche Amministrazioni","acronimo":"","cf_validato":"S","Cf":"00132100439","mail1":"comune.morrovalle.mc@legalmail.it","tipo_mail1":"pec","mail2":"comune@morrovalle.org","tipo_mail2":"altro","mail3":"null","tipo_mail3":"null","mail4":"null","tipo_mail4":"null","mail5":"null","tipo_mail5":"null","url_facebook":"","url_twitter":"","url_googleplus":"","url_youtube":"","liv_accessibili":"0"}
