{"cod_amm":"c_h417","des_amm":"Comune di Roccalbegna","Comune":"Roccalbegna","nome_resp":"Massimo","cogn_resp":"Galli","Cap":"58053","Provincia":"GR","Regione":"Toscana","sito_istituzionale":"www.comune.roccalbegna.gr.it","Indirizzo":"Piazza Marconi, 51","titolo_resp":"sindaco","tipologia_istat":"Comuni e loro Consorzi e Associazioni","tipologia_amm":"Pubbliche Amministrazioni","acronimo":"","cf_validato":"S","Cf":"00117330530","mail1":"Comune.roccalbegna@postacert.toscana.it","tipo_mail1":"pec","mail2":"null","tipo_mail2":"null","mail3":"null","tipo_mail3":"null","mail4":"null","tipo_mail4":"null","mail5":"null","tipo_mail5":"null","url_facebook":"","url_twitter":"","url_googleplus":"","url_youtube":"","liv_accessibili":"0"}
